mhc/__init__.py
mhc/hyper_connection.py
mhc/sinkhorn_knopp.py
mhc_pytorch-0.2.3.dist-info/LICENSE
mhc_pytorch-0.2.3.dist-info/METADATA
mhc_pytorch-0.2.3.dist-info/WHEEL
mhc_pytorch-0.2.3.dist-info/RECORD
