Metadata-Version: 2.1
Name: mhc-pytorch
Version: 0.2.3
Summary: A PyTorch implementation of Manifold-Constrained Hyper-Connections (mHC), a multi-stream residual connection mechanism for deep learning models with mathematical constraints.
Home-page: https://github.com/KennyStryker/manifold-constrained-hyper-connections.git
License: MIT
Author: Kenny Stryker
Author-email: nggkenny@gmail.com
Requires-Python: >=3.12,<3.15
Classifier: Development Status :: 4 - Beta
Classifier: Intended Audience :: Science/Research
Classifier: License :: OSI Approved :: MIT License
Classifier: Natural Language :: English
Classifier: Operating System :: OS Independent
Classifier: Programming Language :: Python :: 3
Classifier: Programming Language :: Python :: 3.12
Classifier: Programming Language :: Python :: 3.13
Classifier: Topic :: Scientific/Engineering :: Artificial Intelligence
Classifier: Topic :: Software Development :: Libraries
Classifier: Typing :: Typed
Requires-Dist: numpy (>=2.4.1,<3.0.0)
Requires-Dist: torch (>=2.9.0,<3.0.0)
Project-URL: Repository, https://github.com/KennyStryker/manifold-constrained-hyper-connections.git
